clinance/__init__.py
clinance/cli.py
clinance/commands.py
clinance-0.1.0.dist-info/METADATA
clinance-0.1.0.dist-info/RECORD
clinance-0.1.0.dist-info/WHEEL
clinance-0.1.0.dist-info/dependency_links.txt
clinance-0.1.0.dist-info/entry_points.txt
clinance-0.1.0.dist-info/top_level.txt
