Metadata-Version: 2.1
Name: clinance
Version: 0.1.0
Summary: Binance client from CLI.
Home-page: https://github.com/havocesp/clinance
Author: Daniel J. Umpierrez
Author-email: UNKNOWN
License: MIT
Keywords: binance cli terminal console client trading altcoin exchange finance market bitcoin cryptocurrency cryptocurrencies crypto-currencies crypto-currency
Platform: UNKNOWN
Classifier: Development Status :: 4 - Beta
Classifier: License :: OSI Approved :: MIT License
Classifier: Programming Language :: Python :: 3.5
Classifier: Programming Language :: Python :: 3.6
Classifier: Programming Language :: Python :: 3.7
Requires-Dist: panance
Requires-Dist: finta
Requires-Dist: tabulate
Requires-Dist: defopt
